pywright_gpt_chat/__init__.py
pywright_gpt_chat-0.0.4.dist-info/METADATA
pywright_gpt_chat-0.0.4.dist-info/WHEEL
pywright_gpt_chat-0.0.4.dist-info/top_level.txt
pywright_gpt_chat-0.0.4.dist-info/RECORD
