Metadata-Version: 2.4
Name: pywright-gpt-chat
Version: 0.0.4
Summary: Python Module for Free ChatGPT Chat
Author-email: Abdullah Al Jaber <abdullah.0.al.0.jaber@gmail.com>
Project-URL: Source Code, https://github.com/abdullah-al-jaber/pywright-gpt-chat
Requires-Python: >=3.10
